fpvgcc/__init__.py
fpvgcc/cli.py
fpvgcc/fpv.py
fpvgcc/gccMemoryMap.py
fpvgcc/datastructures/__init__.py
fpvgcc/datastructures/ntree.py
fpvgcc/datastructures/ntreeSize.py
fpvgcc/profiles/__init__.py
fpvgcc/profiles/context.py
fpvgcc/profiles/gcc_msp430.py
fpvgcc/profiles/guess.py
fpvgcc-1.0.0.dist-info/LICENSE
fpvgcc-1.0.0.dist-info/METADATA
fpvgcc-1.0.0.dist-info/WHEEL
fpvgcc-1.0.0.dist-info/entry_points.txt
fpvgcc-1.0.0.dist-info/top_level.txt
fpvgcc-1.0.0.dist-info/RECORD
